easyclient/__init__.py
easyclient/statics.py
easyclient/utils.py
easyclient/client/__init__.py
easyclient/client/base/__init__.py
easyclient/client/base/auth.py
easyclient/client/base/client.py
easyclient/client/rest/__init__.py
easyclient/client/rest/client.py
easyclient/parameters/__init__.py
easyclient-0.1.1.dist-info/METADATA
easyclient-0.1.1.dist-info/WHEEL
easyclient-0.1.1.dist-info/top_level.txt
easyclient-0.1.1.dist-info/RECORD
