Metadata-Version: 2.1
Name: easyclient
Version: 0.1.1
Summary: A simple boilerplate for making REST API clients.
Home-page: https://github.com/nwithan8/easyclient
Download-URL: https://github.com/nwithan8/easyclient/archive/refs/tags/0.1.1.tar.gz
Author: Nate Harris
Author-email: n8gr8gbln@gmail.com
License: GNU General Public License v3 (GPLv3)
Keywords: API,client,JSON,Pydantic,REST,boilerplate
Classifier: License :: OSI Approved :: GNU General Public License v3 (GPLv3)
Classifier: Development Status :: 4 - Beta
Classifier: Intended Audience :: Developers
Classifier: Topic :: Software Development :: Build Tools
Classifier: Programming Language :: Python :: 3
Classifier: Programming Language :: Python :: 3.7
Classifier: Programming Language :: Python :: 3.8
Classifier: Programming Language :: Python :: 3.9
Classifier: Programming Language :: Python :: 3.10
Classifier: Programming Language :: Python :: 3.11
Classifier: Topic :: Multimedia :: Video
Classifier: Topic :: Multimedia
Classifier: Topic :: Internet :: WWW/HTTP
Classifier: Operating System :: OS Independent
Requires-Python: >=3.7, <4
Requires-Dist: objectrest (==2.0.*)
Requires-Dist: pytz (==2022.1.*)
Requires-Dist: packaging (==21.3.*)
Requires-Dist: typing-extensions
Provides-Extra: dev
Requires-Dist: black ; extra == 'dev'
Requires-Dist: flake8 ; extra == 'dev'
Requires-Dist: isort ; extra == 'dev'
Requires-Dist: pytest-cov (==3.*) ; extra == 'dev'
Requires-Dist: pytest-vcr (==1.*) ; extra == 'dev'
Requires-Dist: pytest (==7.*) ; extra == 'dev'
Requires-Dist: types-requests ; extra == 'dev'
Requires-Dist: types-urllib3 ; extra == 'dev'
Requires-Dist: vcrpy (==4.*) ; extra == 'dev'
